immunogen/__init__.py
immunogen/config.ini
immunogen/data/HLAConversionDataDictionary.csv
immunogen/data/__init__.py
immunogen/data/aligned_sequences.csv
immunogen/data/amino_acids.csv
immunogen/data/class_ii_sequences/DPA1_seq.csv
immunogen/data/class_ii_sequences/DPB1_seq.csv
immunogen/data/class_ii_sequences/DQA1_seq.csv
immunogen/data/class_ii_sequences/DQB1_seq.csv
immunogen/data/class_ii_sequences/DRB1345_seq.csv
immunogen/data/eplets/allele_eplet_type.csv
immunogen/data/haplotype_frequencies/AFA.csv
immunogen/data/haplotype_frequencies/API.csv
immunogen/data/haplotype_frequencies/CAU.csv
immunogen/data/haplotype_frequencies/HIS.csv
immunogen/data/haplotype_frequencies/NAM.csv
immunogen/data/pickles/__init__.py
immunogen/data/pickles/aligned_sequences.p
immunogen/data/pickles/allele_conversions.p
immunogen/data/pickles/allele_mappings.p
immunogen/data/pickles/allele_sequences.p
immunogen/data/pickles/amino_acids.p
immunogen/data/pickles/eplet_types.p
immunogen/data/pickles/eplets.p
immunogen/data/pickles/haplotype_frequencies.p
immunogen/eplets/__init__.py
immunogen/eplets/eplets.py
immunogen/immunogenicity/__init__.py
immunogen/immunogenicity/immunogenicity.py
immunogen/utils/MetaLogger.py
immunogen/utils/__init__.py
immunogen-0.1.0.dist-info/WHEEL
immunogen-0.1.0.dist-info/METADATA
immunogen-0.1.0.dist-info/RECORD
